azip/__init__.py
azip/_version.py
azip/azip.py
azip-1.0.1.dist-info/LICENSE
azip-1.0.1.dist-info/METADATA
azip-1.0.1.dist-info/WHEEL
azip-1.0.1.dist-info/top_level.txt
azip-1.0.1.dist-info/RECORD
