Metadata-Version: 2.1
Name: azip
Version: 1.0.1
Summary: zip operator for async iterables
Home-page: https://gitlab.com/martizih/azip.git
Author: Martin Zihlmann
Author-email: martizih@outlook.com
License: MIT
Classifier: Programming Language :: Python :: 3
Classifier: License :: Other/Proprietary License
Classifier: Operating System :: OS Independent
Requires-Python: >=3
License-File: LICENSE
